supDolphinWS/__init__.py
supDolphinWS/server/__init__.py
supDolphinWS/server/__main__.py
supDolphinWS/server/api.py
supDolphinWS/server/dolphin.py
supDolphinWS/server/err.py
supDolphinWS/server/memory_windows.py
supDolphinWS/server/server.py
supDolphinWS/server/utils.py
supDolphinWS_server-0.1.3.dist-info/LICENSE
supDolphinWS_server-0.1.3.dist-info/METADATA
supDolphinWS_server-0.1.3.dist-info/WHEEL
supDolphinWS_server-0.1.3.dist-info/top_level.txt
supDolphinWS_server-0.1.3.dist-info/RECORD
