Metadata-Version: 2.1
Name: supDolphinWS-server
Version: 0.1.3
Summary: A WebSocket server for accessing memory of emulated games in Dolphin
Home-page: https://github.com/sup39/supDolphinWS-server
Author: sup39
Author-email: sms@sup39.dev
License: MIT
Project-URL: Bug Tracker, https://github.com/sup39/supDolphinWS-server/issues
Classifier: Programming Language :: Python :: 3
Classifier: License :: OSI Approved :: MIT License
Classifier: Operating System :: Microsoft :: Windows
Requires-Python: >=3.8
License-File: LICENSE
Requires-Dist: wsocket (>=2.1.0)
Requires-Dist: psutil (>=5.9.4)
